poet/__init__.py
poet/_compat.py
poet/installer.py
poet/locations.py
poet/lock.py
poet/poet.py
poet/publisher.py
poet/version_parser.py
poet/version_selector.py
poet/build/__init__.py
poet/build/builder.py
poet/console/__init__.py
poet/console/application.py
poet/console/commands/__init__.py
poet/console/commands/about.py
poet/console/commands/check.py
poet/console/commands/command.py
poet/console/commands/index_command.py
poet/console/commands/init.py
poet/console/commands/install.py
poet/console/commands/lock.py
poet/console/commands/package.py
poet/console/commands/publish.py
poet/console/commands/require.py
poet/console/commands/search.py
poet/console/commands/update.py
poet/console/commands/make/__init__.py
poet/console/commands/make/requirements.py
poet/console/commands/make/setup.py
poet/exceptions/__init__.py
poet/exceptions/poet.py
poet/package/__init__.py
poet/package/dependency.py
poet/package/package.py
poet/package/pip_dependency.py
poet/repositories/__init__.py
poet/repositories/pypi_repository.py
poet/templates/poetry.lock.jinja2
poet/templates/poetry.toml.jinja2
poet/templates/setup.py.jinja2
poet/utils/__init__.py
poet/utils/helpers.py
poet/utils/lexers.py
pypoet-0.4.1.dist-info/DESCRIPTION.rst
pypoet-0.4.1.dist-info/METADATA
pypoet-0.4.1.dist-info/RECORD
pypoet-0.4.1.dist-info/WHEEL
pypoet-0.4.1.dist-info/entry_points.txt
pypoet-0.4.1.dist-info/metadata.json
pypoet-0.4.1.dist-info/top_level.txt
