Metadata-Version: 2.0
Name: pypoet
Version: 0.4.1
Summary: Poet helps you declare, manage and install dependencies of Python projects, ensuring you have the right stack everywhere.
Home-page: https://github.com/sdispater/poet
Author: Sébastien Eustace
Author-email: sebastien@eustace.io
License: MIT
Keywords: packaging poet
Platform: UNKNOWN
Classifier: Programming Language :: Python
Classifier: Programming Language :: Python :: 2
Classifier: Programming Language :: Python :: 2.7
Classifier: Programming Language :: Python :: 3
Classifier: Programming Language :: Python :: 3.5
Classifier: Programming Language :: Python :: 3.6
Requires-Dist: cleo (<0.7.0,>=0.6.0)
Requires-Dist: jinja2 (>=2.9.6,<3.0.0)
Requires-Dist: packaging (<17.0.0,>=16.8.0)
Requires-Dist: pathlib2 (<3.0.0,>=2.2.0)
Requires-Dist: pip-tools (<2.0.0,>=1.9.0)
Requires-Dist: pygments (<3.0.0,>=2.2.0)
Requires-Dist: requests (<3.0.0,>=2.13.0)
Requires-Dist: requests-toolbelt (>=0.7.0,<0.8.0)
Requires-Dist: semantic-version (<3.0.0,>=2.6.0)
Requires-Dist: toml (<0.10.0,>=0.9.0)
Requires-Dist: twine (<2.0.0,>=1.8.0)
Requires-Dist: wheel (<0.30.0,>=0.29.0)
Provides-Extra: markdown-readme
Requires-Dist: pypandoc (<2.0.0,>=1.3.3); extra == 'markdown-readme'
